yk_bit/__init__.py
yk_bit/bit.py
yk_bit/utils.py
yk_bit-2.0.0.dist-info/LICENSE
yk_bit-2.0.0.dist-info/METADATA
yk_bit-2.0.0.dist-info/WHEEL
yk_bit-2.0.0.dist-info/top_level.txt
yk_bit-2.0.0.dist-info/RECORD
