Metadata-Version: 2.1
Name: yk-bit
Version: 2.0.0
Summary: Python SDK for the Youverse BiometricInThings API.
Home-page: https://github.com/dev-yoonik/YK-BiT-SDK-Python
Author: Youverse
Author-email: tech@youverse.id
License: MIT
Classifier: Programming Language :: Python :: 3
Classifier: License :: OSI Approved :: MIT License
Classifier: Operating System :: OS Independent
Requires-Python: >=3.6
License-File: LICENSE
Requires-Dist: six
Requires-Dist: requests
Requires-Dist: setuptools
Requires-Dist: yk-utils (<2,>=1.1.4)
Requires-Dist: yk-bit-api-model (<2,>=1.3.3)
